[
  {
    "User": "Daniela Kent",
    "User Status": "Engaged",
    "Outbound Calls": "5",
    "Outbound Calls Answered": "4",
    "Outbound Calls Answered %": "80%",
    "Outbound Duration": "18s",
    "Inbound Calls": "0",
    "Inbound Calls Answered": "0",
    "Inbound Calls Answered %": "0",
    "Inbound Duration": "0",
    "Total Calls": "5",
    "Total Duration": "18s"
  },
  {
    "User": "Hannah Lawry",
    "User Status": "Engaged",
    "Outbound Calls": "3",
    "Outbound Calls Answered": "1",
    "Outbound Calls Answered %": "33%",
    "Outbound Duration": "2s",
    "Inbound Calls": "0",
    "Inbound Calls Answered": "0",
    "Inbound Calls Answered %": "0",
    "Inbound Duration": "0",
    "Total Calls": "3",
    "Total Duration": "2s"
  },
  {
    "User": "Oscar Dixon-Barrow",
    "User Status": "Available",
    "Outbound Calls": "3",
    "Outbound Calls Answered": "3",
    "Outbound Calls Answered %": "100%",
    "Outbound Duration": "1m 51s",
    "Inbound Calls": "0",
    "Inbound Calls Answered": "0",
    "Inbound Calls Answered %": "0",
    "Inbound Duration": "0",
    "Total Calls": "3",
    "Total Duration": "1m 51s"
  },
  {
    "User": "Elaine Connell",
    "User Status": "Available",
    "Outbound Calls": "2",
    "Outbound Calls Answered": "2",
    "Outbound Calls Answered %": "100%",
    "Outbound Duration": "3m 11s",
    "Inbound Calls": "0",
    "Inbound Calls Answered": "0",
    "Inbound Calls Answered %": "0",
    "Inbound Duration": "0",
    "Total Calls": "2",
    "Total Duration": "3m 11s"
  },
  {
    "User": "Jack Perks",
    "User Status": "Engaged",
    "Outbound Calls": "2",
    "Outbound Calls Answered": "2",
    "Outbound Calls Answered %": "100%",
    "Outbound Duration": "9m 19s",
    "Inbound Calls": "0",
    "Inbound Calls Answered": "0",
    "Inbound Calls Answered %": "0",
    "Inbound Duration": "0",
    "Total Calls": "2",
    "Total Duration": "9m 19s"
  },
  {
    "User": "Molly McGuire",
    "User Status": "Available",
    "Outbound Calls": "2",
    "Outbound Calls Answered": "2",
    "Outbound Calls Answered %": "100%",
    "Outbound Duration": "6m 38s",
    "Inbound Calls": "1",
    "Inbound Calls Answered": "1",
    "Inbound Calls Answered %": "100%",
    "Inbound Duration": "11m 8s",
    "Total Calls": "3",
    "Total Duration": "17m 46s"
  },
  {
    "User": "Martha Cumiskey",
    "User Status": "Available",
    "Outbound Calls": "2",
    "Outbound Calls Answered": "2",
    "Outbound Calls Answered %": "100%",
    "Outbound Duration": "7m 1s",
    "Inbound Calls": "1",
    "Inbound Calls Answered": "1",
    "Inbound Calls Answered %": "100%",
    "Inbound Duration": "2m 26s",
    "Total Calls": "3",
    "Total Duration": "9m 27s"
  },
  {
    "User": "Matt Owen",
    "User Status": "Available",
    "Outbound Calls": "2",
    "Outbound Calls Answered": "2",
    "Outbound Calls Answered %": "100%",
    "Outbound Duration": "3m 4s",
    "Inbound Calls": "0",
    "Inbound Calls Answered": "0",
    "Inbound Calls Answered %": "0",
    "Inbound Duration": "0",
    "Total Calls": "2",
    "Total Duration": "3m 4s"
  }
]